Products.LDAPUserFolder-5.2-py3.11-nspkg.pth
Products/LDAPUserFolder/LDAPDelegate.py
Products/LDAPUserFolder/LDAPUser.py
Products/LDAPUserFolder/LDAPUserFolder.py
Products/LDAPUserFolder/__init__.py
Products/LDAPUserFolder/cache.py
Products/LDAPUserFolder/configure.zcml
Products/LDAPUserFolder/exportimport.py
Products/LDAPUserFolder/interfaces.py
Products/LDAPUserFolder/permissions.py
Products/LDAPUserFolder/utils.py
Products/LDAPUserFolder/dtml/cache.dtml
Products/LDAPUserFolder/dtml/groups.dtml
Products/LDAPUserFolder/dtml/ldapschema.dtml
Products/LDAPUserFolder/dtml/properties.dtml
Products/LDAPUserFolder/dtml/sat_cache.dtml
Products/LDAPUserFolder/dtml/servers.dtml
Products/LDAPUserFolder/dtml/users.dtml
Products/LDAPUserFolder/tests/__init__.py
Products/LDAPUserFolder/tests/config.py
Products/LDAPUserFolder/tests/test.jpg
Products/LDAPUserFolder/tests/test_LDAPDelegate.py
Products/LDAPUserFolder/tests/test_LDAPUser.py
Products/LDAPUserFolder/tests/test_LDAPUserFolder.py
Products/LDAPUserFolder/tests/test_authentication.py
Products/LDAPUserFolder/tests/test_cache.py
Products/LDAPUserFolder/tests/test_exportimport.py
Products/LDAPUserFolder/tests/test_group_role.py
Products/LDAPUserFolder/tests/test_schemamanagement.py
Products/LDAPUserFolder/tests/test_servermanagement.py
Products/LDAPUserFolder/tests/test_utils.py
Products/LDAPUserFolder/tests/base/__init__.py
Products/LDAPUserFolder/tests/base/dummy.py
Products/LDAPUserFolder/tests/base/testcase.py
Products.LDAPUserFolder-5.2.dist-info/LICENSE.txt
Products.LDAPUserFolder-5.2.dist-info/METADATA
Products.LDAPUserFolder-5.2.dist-info/WHEEL
Products.LDAPUserFolder-5.2.dist-info/entry_points.txt
Products.LDAPUserFolder-5.2.dist-info/namespace_packages.txt
Products.LDAPUserFolder-5.2.dist-info/top_level.txt
Products.LDAPUserFolder-5.2.dist-info/RECORD
